[{"line":1,"elements":[{"start_timestamp":"2023-09-01T18:39:01.237Z","before":[{"result":{"duration":5829621500,"status":"passed"},"match":{"location":"com.training.steps.Steps.setup()"}}],"line":4,"name":"Checking Oppurtunity dropdown","description":"","id":"oppurtunities-scenarios-of-salesforce-application;checking-oppurtunity-dropdown","type":"scenario","keyword":"Scenario","steps":[{"result":{"duration":9941000,"status":"passed"},"line":5,"name":"User is in the \"LoginPage\"","match":{"arguments":[{"val":"\"LoginPage\"","offset":15}],"location":"com.training.steps.Steps.user_is_in_the(java.lang.String)"},"keyword":"Given "},{"result":{"duration":830729800,"status":"passed"},"line":6,"name":"User enter into Textbox \"Username\" \"Myself@HomeComp.org\"","match":{"arguments":[{"val":"\"Username\"","offset":24},{"val":"\"Myself@HomeComp.org\"","offset":35}],"location":"com.training.steps.Steps.user_enter_into_textbox(java.lang.String,java.lang.String)"},"keyword":"When "},{"result":{"duration":656146500,"status":"passed"},"line":7,"name":"User enter into Textbox \"Password\" \"Really82\"","match":{"arguments":[{"val":"\"Password\"","offset":24},{"val":"\"Really82\"","offset":35}],"location":"com.training.steps.Steps.user_enter_into_textbox(java.lang.String,java.lang.String)"},"keyword":"When "},{"result":{"duration":2474130400,"status":"passed"},"line":8,"name":"User Clicks on Button \"Login\"","match":{"arguments":[{"val":"\"Login\"","offset":22}],"location":"com.training.steps.Steps.user_clicks_on_button(java.lang.String)"},"keyword":"Then "},{"result":{"duration":1995000,"status":"passed"},"line":9,"name":"User is in the \"OppurtunitiesPage\"","match":{"arguments":[{"val":"\"OppurtunitiesPage\"","offset":15}],"location":"com.training.steps.Steps.user_is_in_the(java.lang.String)"},"keyword":"Given "},{"result":{"duration":4295183200,"status":"passed"},"line":10,"name":"User Clicks on Tab \"Oppurtunities\"","match":{"arguments":[{"val":"\"Oppurtunities\"","offset":19}],"location":"com.training.steps.Steps.user_clicks_on_tab(java.lang.String)"},"keyword":"Then "},{"result":{"error_message":"org.openqa.selenium.NoSuchElementException: no such element: Unable to locate element: {\"method\":\"xpath\",\"selector\":\"//a[@id='tryLexDialogX']\"}\n  (Session info: chrome=116.0.5845.112)\nFor documentation on this error, please visit: https://www.seleniumhq.org/exceptions/no_such_element.html\nBuild info: version: '3.141.59', revision: 'e82be7d358', time: '2018-11-14T08:17:03'\nSystem info: host: 'DESKTOP-SHP5I9E', ip: '192.168.1.68', os.name: 'Windows 10', os.arch: 'amd64', os.version: '10.0', java.version: '17.0.6'\nDriver info: org.openqa.selenium.chrome.ChromeDriver\nCapabilities {acceptInsecureCerts: false, browserName: chrome, browserVersion: 116.0.5845.112, chrome: {chromedriverVersion: 116.0.5845.96 (1a3918166880..., userDataDir: C:\\Users\\User\\AppData\\Local...}, fedcm:accounts: true, goog:chromeOptions: {debuggerAddress: localhost:60533}, javascriptEnabled: true, networkConnectionEnabled: false, pageLoadStrategy: normal, platform: WINDOWS, platformName: WINDOWS, proxy: Proxy(), setWindowRect: true, strictFileInteractability: false, timeouts: {implicit: 0, pageLoad: 300000, script: 30000}, unhandledPromptBehavior: dismiss and notify, webauthn:extension:credBlob: true, webauthn:extension:largeBlob: true, webauthn:extension:minPinLength: true, webauthn:extension:prf: true, webauthn:virtualAuthenticators: true}\nSession ID: 671b82b876cb7e1fa2a24321bb861806\n*** Element info: {Using=xpath, value=//a[@id='tryLexDialogX']}\r\n\tat java.base/jdk.internal.reflect.NativeConstructorAccessorImpl.newInstance0(Native Method)\r\n\tat java.base/jdk.internal.reflect.NativeConstructorAccessorImpl.newInstance(NativeConstructorAccessorImpl.java:77)\r\n\tat java.base/jdk.internal.reflect.DelegatingConstructorAccessorImpl.newInstance(DelegatingConstructorAccessorImpl.java:45)\r\n\tat java.base/java.lang.reflect.Constructor.newInstanceWithCaller(Constructor.java:499)\r\n\tat java.base/java.lang.reflect.Constructor.newInstance(Constructor.java:480)\r\n\tat org.openqa.selenium.remote.http.W3CHttpResponseCodec.createException(W3CHttpResponseCodec.java:187)\r\n\tat org.openqa.selenium.remote.http.W3CHttpResponseCodec.decode(W3CHttpResponseCodec.java:122)\r\n\tat org.openqa.selenium.remote.http.W3CHttpResponseCodec.decode(W3CHttpResponseCodec.java:49)\r\n\tat org.openqa.selenium.remote.HttpCommandExecutor.execute(HttpCommandExecutor.java:158)\r\n\tat org.openqa.selenium.remote.service.DriverCommandExecutor.execute(DriverCommandExecutor.java:83)\r\n\tat org.openqa.selenium.remote.RemoteWebDriver.execute(RemoteWebDriver.java:552)\r\n\tat org.openqa.selenium.remote.RemoteWebDriver.findElement(RemoteWebDriver.java:323)\r\n\tat org.openqa.selenium.remote.RemoteWebDriver.findElementByXPath(RemoteWebDriver.java:428)\r\n\tat org.openqa.selenium.By$ByXPath.findElement(By.java:353)\r\n\tat org.openqa.selenium.remote.RemoteWebDriver.findElement(RemoteWebDriver.java:315)\r\n\tat com.training.base.BasePage.getElement(BasePage.java:45)\r\n\tat com.training.base.BasePage.promptclose(BasePage.java:204)\r\n\tat com.training.steps.Steps.user_closes_prompt_display(Steps.java:105)\r\n\tat ✽.User Closes PromptDisplay \"Prompt\"(file:///C:/Users/User/eclipse-workspace/JavaBasic/CucumberSalesForceFramework/features/Oppurtunities.feature:11)\r\n","duration":311674900,"status":"failed"},"line":11,"name":"User Closes PromptDisplay \"Prompt\"","match":{"arguments":[{"val":"\"Prompt\"","offset":26}],"location":"com.training.steps.Steps.user_closes_prompt_display(java.lang.String)"},"keyword":"Then "},{"result":{"status":"skipped"},"line":12,"name":"Check for DropDown ViewList \"OppViewList\"","match":{"arguments":[{"val":"\"OppViewList\"","offset":28}],"location":"com.training.steps.Steps.check_for_drop_down_viewlist(java.lang.String)"},"keyword":"Then "}],"tags":[{"name":"@TC15"}]},{"start_timestamp":"2023-09-01T18:39:15.846Z","before":[{"result":{"duration":1684253300,"status":"passed"},"match":{"location":"com.training.steps.Steps.setup()"}}],"line":16,"name":"Creating New Oppurtunity","description":"","id":"oppurtunities-scenarios-of-salesforce-application;creating-new-oppurtunity","type":"scenario","keyword":"Scenario","steps":[{"result":{"duration":1993900,"status":"passed"},"line":17,"name":"User is in the \"LoginPage\"","match":{"arguments":[{"val":"\"LoginPage\"","offset":15}],"location":"com.training.steps.Steps.user_is_in_the(java.lang.String)"},"keyword":"Given "},{"result":{"duration":762275800,"status":"passed"},"line":18,"name":"User enter into Textbox \"Username\" \"Myself@HomeComp.org\"","match":{"arguments":[{"val":"\"Username\"","offset":24},{"val":"\"Myself@HomeComp.org\"","offset":35}],"location":"com.training.steps.Steps.user_enter_into_textbox(java.lang.String,java.lang.String)"},"keyword":"When "},{"result":{"duration":666507700,"status":"passed"},"line":19,"name":"User enter into Textbox \"Password\" \"Really82\"","match":{"arguments":[{"val":"\"Password\"","offset":24},{"val":"\"Really82\"","offset":35}],"location":"com.training.steps.Steps.user_enter_into_textbox(java.lang.String,java.lang.String)"},"keyword":"When "},{"result":{"duration":1781099900,"status":"passed"},"line":20,"name":"User Clicks on Button \"Login\"","match":{"arguments":[{"val":"\"Login\"","offset":22}],"location":"com.training.steps.Steps.user_clicks_on_button(java.lang.String)"},"keyword":"Then "},{"result":{"duration":2007900,"status":"passed"},"line":21,"name":"User is in the \"OppurtunitiesPage\"","match":{"arguments":[{"val":"\"OppurtunitiesPage\"","offset":15}],"location":"com.training.steps.Steps.user_is_in_the(java.lang.String)"},"keyword":"Given "},{"result":{"duration":1952255800,"status":"passed"},"line":22,"name":"User Clicks on Tab \"Oppurtunities\"","match":{"arguments":[{"val":"\"Oppurtunities\"","offset":19}],"location":"com.training.steps.Steps.user_clicks_on_tab(java.lang.String)"},"keyword":"Then "},{"result":{"duration":1070400700,"status":"passed"},"line":23,"name":"User Closes PromptDisplay \"Prompt\"","match":{"arguments":[{"val":"\"Prompt\"","offset":26}],"location":"com.training.steps.Steps.user_closes_prompt_display(java.lang.String)"},"keyword":"Then "},{"result":{"duration":1619725800,"status":"passed"},"line":24,"name":"User Clicks on Button \"New\"","match":{"arguments":[{"val":"\"New\"","offset":22}],"location":"com.training.steps.Steps.user_clicks_on_button(java.lang.String)"},"keyword":"Then "},{"result":{"duration":597881300,"status":"passed"},"line":25,"name":"User enter into Textbox \"OppName\" \"Oppurtunity6\"","match":{"arguments":[{"val":"\"OppName\"","offset":24},{"val":"\"Oppurtunity6\"","offset":34}],"location":"com.training.steps.Steps.user_enter_into_textbox(java.lang.String,java.lang.String)"},"keyword":"Then "},{"result":{"duration":617395800,"status":"passed"},"line":26,"name":"User enter into Textbox \"AccName\" \"Naidu\"","match":{"arguments":[{"val":"\"AccName\"","offset":24},{"val":"\"Naidu\"","offset":34}],"location":"com.training.steps.Steps.user_enter_into_textbox(java.lang.String,java.lang.String)"},"keyword":"Then "},{"result":{"duration":1093685700,"status":"passed"},"line":27,"name":"User Clicks on \"CloseDateField\"","match":{"arguments":[{"val":"\"CloseDateField\"","offset":15}],"location":"com.training.steps.Steps.user_clicks_on(java.lang.String)"},"keyword":"Then "},{"result":{"duration":152629500,"status":"passed"},"line":28,"name":"User selects value from Dropdown \"SelectMonth\" \"December\"","match":{"arguments":[{"val":"\"SelectMonth\"","offset":33},{"val":"\"December\"","offset":47}],"location":"com.training.steps.Steps.user_selects_value_from_dropdown(java.lang.String,java.lang.String)"},"keyword":"Then "},{"result":{"duration":120690700,"status":"passed"},"line":29,"name":"User selects value from Dropdown \"SelectYear\" \"2024\"","match":{"arguments":[{"val":"\"SelectYear\"","offset":33},{"val":"\"2024\"","offset":46}],"location":"com.training.steps.Steps.user_selects_value_from_dropdown(java.lang.String,java.lang.String)"},"keyword":"Then "},{"result":{"duration":1081314700,"status":"passed"},"line":30,"name":"User Clicks on \"Date\"","match":{"arguments":[{"val":"\"Date\"","offset":15}],"location":"com.training.steps.Steps.user_clicks_on(java.lang.String)"},"keyword":"Then "},{"result":{"duration":130188300,"status":"passed"},"line":31,"name":"User selects value from Dropdown \"Stage\" \"Qualification\"","match":{"arguments":[{"val":"\"Stage\"","offset":33},{"val":"\"Qualification\"","offset":41}],"location":"com.training.steps.Steps.user_selects_value_from_dropdown(java.lang.String,java.lang.String)"},"keyword":"Then "},{"result":{"duration":606519500,"status":"passed"},"line":32,"name":"User enter into Textbox \"Probability\" \"90\"","match":{"arguments":[{"val":"\"Probability\"","offset":24},{"val":"\"90\"","offset":38}],"location":"com.training.steps.Steps.user_enter_into_textbox(java.lang.String,java.lang.String)"},"keyword":"Then "},{"result":{"duration":142618900,"status":"passed"},"line":33,"name":"User selects value from Dropdown \"LeadSource\" \"Web\"","match":{"arguments":[{"val":"\"LeadSource\"","offset":33},{"val":"\"Web\"","offset":46}],"location":"com.training.steps.Steps.user_selects_value_from_dropdown(java.lang.String,java.lang.String)"},"keyword":"Then "},{"result":{"duration":2303206600,"status":"passed"},"line":34,"name":"User Clicks on Button \"Save\"","match":{"arguments":[{"val":"\"Save\"","offset":22}],"location":"com.training.steps.Steps.user_clicks_on_button(java.lang.String)"},"keyword":"Then "}],"tags":[{"name":"@TC16"}]},{"start_timestamp":"2023-09-01T18:39:32.260Z","before":[{"result":{"duration":151132800,"status":"passed"},"match":{"location":"com.training.steps.Steps.setup()"}}],"line":38,"name":"Test Oppurtunity PipeLine","description":"","id":"oppurtunities-scenarios-of-salesforce-application;test-oppurtunity-pipeline","type":"scenario","keyword":"Scenario","steps":[{"result":{"duration":1000300,"status":"passed"},"line":39,"name":"User is in the \"LoginPage\"","match":{"arguments":[{"val":"\"LoginPage\"","offset":15}],"location":"com.training.steps.Steps.user_is_in_the(java.lang.String)"},"keyword":"Given "},{"result":{"duration":638969000,"status":"passed"},"line":40,"name":"User enter into Textbox \"Username\" \"Myself@HomeComp.org\"","match":{"arguments":[{"val":"\"Username\"","offset":24},{"val":"\"Myself@HomeComp.org\"","offset":35}],"location":"com.training.steps.Steps.user_enter_into_textbox(java.lang.String,java.lang.String)"},"keyword":"When "},{"result":{"duration":602123200,"status":"passed"},"line":41,"name":"User enter into Textbox \"Password\" \"Really82\"","match":{"arguments":[{"val":"\"Password\"","offset":24},{"val":"\"Really82\"","offset":35}],"location":"com.training.steps.Steps.user_enter_into_textbox(java.lang.String,java.lang.String)"},"keyword":"When "},{"result":{"duration":1901081000,"status":"passed"},"line":42,"name":"User Clicks on Button \"Login\"","match":{"arguments":[{"val":"\"Login\"","offset":22}],"location":"com.training.steps.Steps.user_clicks_on_button(java.lang.String)"},"keyword":"Then "},{"result":{"duration":1994700,"status":"passed"},"line":43,"name":"User is in the \"OppurtunitiesPage\"","match":{"arguments":[{"val":"\"OppurtunitiesPage\"","offset":15}],"location":"com.training.steps.Steps.user_is_in_the(java.lang.String)"},"keyword":"Given "},{"result":{"duration":2216648100,"status":"passed"},"line":44,"name":"User Clicks on Tab \"Oppurtunities\"","match":{"arguments":[{"val":"\"Oppurtunities\"","offset":19}],"location":"com.training.steps.Steps.user_clicks_on_tab(java.lang.String)"},"keyword":"Then "},{"result":{"error_message":"org.openqa.selenium.NoSuchElementException: no such element: Unable to locate element: {\"method\":\"xpath\",\"selector\":\"//a[@id='tryLexDialogX']\"}\n  (Session info: chrome=116.0.5845.112)\nFor documentation on this error, please visit: https://www.seleniumhq.org/exceptions/no_such_element.html\nBuild info: version: '3.141.59', revision: 'e82be7d358', time: '2018-11-14T08:17:03'\nSystem info: host: 'DESKTOP-SHP5I9E', ip: '192.168.1.68', os.name: 'Windows 10', os.arch: 'amd64', os.version: '10.0', java.version: '17.0.6'\nDriver info: org.openqa.selenium.chrome.ChromeDriver\nCapabilities {acceptInsecureCerts: false, browserName: chrome, browserVersion: 116.0.5845.112, chrome: {chromedriverVersion: 116.0.5845.96 (1a3918166880..., userDataDir: C:\\Users\\User\\AppData\\Local...}, fedcm:accounts: true, goog:chromeOptions: {debuggerAddress: localhost:60533}, javascriptEnabled: true, networkConnectionEnabled: false, pageLoadStrategy: normal, platform: WINDOWS, platformName: WINDOWS, proxy: Proxy(), setWindowRect: true, strictFileInteractability: false, timeouts: {implicit: 0, pageLoad: 300000, script: 30000}, unhandledPromptBehavior: dismiss and notify, webauthn:extension:credBlob: true, webauthn:extension:largeBlob: true, webauthn:extension:minPinLength: true, webauthn:extension:prf: true, webauthn:virtualAuthenticators: true}\nSession ID: 671b82b876cb7e1fa2a24321bb861806\n*** Element info: {Using=xpath, value=//a[@id='tryLexDialogX']}\r\n\tat java.base/jdk.internal.reflect.NativeConstructorAccessorImpl.newInstance0(Native Method)\r\n\tat java.base/jdk.internal.reflect.NativeConstructorAccessorImpl.newInstance(NativeConstructorAccessorImpl.java:77)\r\n\tat java.base/jdk.internal.reflect.DelegatingConstructorAccessorImpl.newInstance(DelegatingConstructorAccessorImpl.java:45)\r\n\tat java.base/java.lang.reflect.Constructor.newInstanceWithCaller(Constructor.java:499)\r\n\tat java.base/java.lang.reflect.Constructor.newInstance(Constructor.java:480)\r\n\tat org.openqa.selenium.remote.http.W3CHttpResponseCodec.createException(W3CHttpResponseCodec.java:187)\r\n\tat org.openqa.selenium.remote.http.W3CHttpResponseCodec.decode(W3CHttpResponseCodec.java:122)\r\n\tat org.openqa.selenium.remote.http.W3CHttpResponseCodec.decode(W3CHttpResponseCodec.java:49)\r\n\tat org.openqa.selenium.remote.HttpCommandExecutor.execute(HttpCommandExecutor.java:158)\r\n\tat org.openqa.selenium.remote.service.DriverCommandExecutor.execute(DriverCommandExecutor.java:83)\r\n\tat org.openqa.selenium.remote.RemoteWebDriver.execute(RemoteWebDriver.java:552)\r\n\tat org.openqa.selenium.remote.RemoteWebDriver.findElement(RemoteWebDriver.java:323)\r\n\tat org.openqa.selenium.remote.RemoteWebDriver.findElementByXPath(RemoteWebDriver.java:428)\r\n\tat org.openqa.selenium.By$ByXPath.findElement(By.java:353)\r\n\tat org.openqa.selenium.remote.RemoteWebDriver.findElement(RemoteWebDriver.java:315)\r\n\tat com.training.base.BasePage.getElement(BasePage.java:45)\r\n\tat com.training.base.BasePage.promptclose(BasePage.java:204)\r\n\tat com.training.steps.Steps.user_closes_prompt_display(Steps.java:105)\r\n\tat ✽.User Closes PromptDisplay \"Prompt\"(file:///C:/Users/User/eclipse-workspace/JavaBasic/CucumberSalesForceFramework/features/Oppurtunities.feature:45)\r\n","duration":23793500,"status":"failed"},"line":45,"name":"User Closes PromptDisplay \"Prompt\"","match":{"arguments":[{"val":"\"Prompt\"","offset":26}],"location":"com.training.steps.Steps.user_closes_prompt_display(java.lang.String)"},"keyword":"Then "},{"result":{"status":"skipped"},"line":46,"name":"User Clicks on \"OppurtunityPipeline\"","match":{"arguments":[{"val":"\"OppurtunityPipeline\"","offset":15}],"location":"com.training.steps.Steps.user_clicks_on(java.lang.String)"},"keyword":"Then "},{"result":{"status":"skipped"},"line":47,"name":"Check for text displayed \"PipeLinePageText\" \"Opportunity Pipeline\"","match":{"arguments":[{"val":"\"PipeLinePageText\"","offset":25},{"val":"\"Opportunity Pipeline\"","offset":44}],"location":"com.training.steps.Steps.check_for_text_displayed(java.lang.String,java.lang.String)"},"keyword":"And "}],"tags":[{"name":"@TC17"}]},{"start_timestamp":"2023-09-01T18:39:37.814Z","before":[{"result":{"duration":143489500,"status":"passed"},"match":{"location":"com.training.steps.Steps.setup()"}}],"line":50,"name":"Test Stuck Oppurtunity","description":"","id":"oppurtunities-scenarios-of-salesforce-application;test-stuck-oppurtunity","type":"scenario","keyword":"Scenario","steps":[{"result":{"duration":1996300,"status":"passed"},"line":51,"name":"User is in the \"LoginPage\"","match":{"arguments":[{"val":"\"LoginPage\"","offset":15}],"location":"com.training.steps.Steps.user_is_in_the(java.lang.String)"},"keyword":"Given "},{"result":{"duration":622282500,"status":"passed"},"line":52,"name":"User enter into Textbox \"Username\" \"Myself@HomeComp.org\"","match":{"arguments":[{"val":"\"Username\"","offset":24},{"val":"\"Myself@HomeComp.org\"","offset":35}],"location":"com.training.steps.Steps.user_enter_into_textbox(java.lang.String,java.lang.String)"},"keyword":"When "},{"result":{"duration":588998200,"status":"passed"},"line":53,"name":"User enter into Textbox \"Password\" \"Really82\"","match":{"arguments":[{"val":"\"Password\"","offset":24},{"val":"\"Really82\"","offset":35}],"location":"com.training.steps.Steps.user_enter_into_textbox(java.lang.String,java.lang.String)"},"keyword":"When "},{"result":{"duration":2034822900,"status":"passed"},"line":54,"name":"User Clicks on Button \"Login\"","match":{"arguments":[{"val":"\"Login\"","offset":22}],"location":"com.training.steps.Steps.user_clicks_on_button(java.lang.String)"},"keyword":"Then "},{"result":{"duration":1992000,"status":"passed"},"line":55,"name":"User is in the \"OppurtunitiesPage\"","match":{"arguments":[{"val":"\"OppurtunitiesPage\"","offset":15}],"location":"com.training.steps.Steps.user_is_in_the(java.lang.String)"},"keyword":"Given "},{"result":{"duration":2391489700,"status":"passed"},"line":56,"name":"User Clicks on Tab \"Oppurtunities\"","match":{"arguments":[{"val":"\"Oppurtunities\"","offset":19}],"location":"com.training.steps.Steps.user_clicks_on_tab(java.lang.String)"},"keyword":"Then "},{"result":{"error_message":"org.openqa.selenium.NoSuchElementException: no such element: Unable to locate element: {\"method\":\"xpath\",\"selector\":\"//a[@id='tryLexDialogX']\"}\n  (Session info: chrome=116.0.5845.112)\nFor documentation on this error, please visit: https://www.seleniumhq.org/exceptions/no_such_element.html\nBuild info: version: '3.141.59', revision: 'e82be7d358', time: '2018-11-14T08:17:03'\nSystem info: host: 'DESKTOP-SHP5I9E', ip: '192.168.1.68', os.name: 'Windows 10', os.arch: 'amd64', os.version: '10.0', java.version: '17.0.6'\nDriver info: org.openqa.selenium.chrome.ChromeDriver\nCapabilities {acceptInsecureCerts: false, browserName: chrome, browserVersion: 116.0.5845.112, chrome: {chromedriverVersion: 116.0.5845.96 (1a3918166880..., userDataDir: C:\\Users\\User\\AppData\\Local...}, fedcm:accounts: true, goog:chromeOptions: {debuggerAddress: localhost:60533}, javascriptEnabled: true, networkConnectionEnabled: false, pageLoadStrategy: normal, platform: WINDOWS, platformName: WINDOWS, proxy: Proxy(), setWindowRect: true, strictFileInteractability: false, timeouts: {implicit: 0, pageLoad: 300000, script: 30000}, unhandledPromptBehavior: dismiss and notify, webauthn:extension:credBlob: true, webauthn:extension:largeBlob: true, webauthn:extension:minPinLength: true, webauthn:extension:prf: true, webauthn:virtualAuthenticators: true}\nSession ID: 671b82b876cb7e1fa2a24321bb861806\n*** Element info: {Using=xpath, value=//a[@id='tryLexDialogX']}\r\n\tat java.base/jdk.internal.reflect.NativeConstructorAccessorImpl.newInstance0(Native Method)\r\n\tat java.base/jdk.internal.reflect.NativeConstructorAccessorImpl.newInstance(NativeConstructorAccessorImpl.java:77)\r\n\tat java.base/jdk.internal.reflect.DelegatingConstructorAccessorImpl.newInstance(DelegatingConstructorAccessorImpl.java:45)\r\n\tat java.base/java.lang.reflect.Constructor.newInstanceWithCaller(Constructor.java:499)\r\n\tat java.base/java.lang.reflect.Constructor.newInstance(Constructor.java:480)\r\n\tat org.openqa.selenium.remote.http.W3CHttpResponseCodec.createException(W3CHttpResponseCodec.java:187)\r\n\tat org.openqa.selenium.remote.http.W3CHttpResponseCodec.decode(W3CHttpResponseCodec.java:122)\r\n\tat org.openqa.selenium.remote.http.W3CHttpResponseCodec.decode(W3CHttpResponseCodec.java:49)\r\n\tat org.openqa.selenium.remote.HttpCommandExecutor.execute(HttpCommandExecutor.java:158)\r\n\tat org.openqa.selenium.remote.service.DriverCommandExecutor.execute(DriverCommandExecutor.java:83)\r\n\tat org.openqa.selenium.remote.RemoteWebDriver.execute(RemoteWebDriver.java:552)\r\n\tat org.openqa.selenium.remote.RemoteWebDriver.findElement(RemoteWebDriver.java:323)\r\n\tat org.openqa.selenium.remote.RemoteWebDriver.findElementByXPath(RemoteWebDriver.java:428)\r\n\tat org.openqa.selenium.By$ByXPath.findElement(By.java:353)\r\n\tat org.openqa.selenium.remote.RemoteWebDriver.findElement(RemoteWebDriver.java:315)\r\n\tat com.training.base.BasePage.getElement(BasePage.java:45)\r\n\tat com.training.base.BasePage.promptclose(BasePage.java:204)\r\n\tat com.training.steps.Steps.user_closes_prompt_display(Steps.java:105)\r\n\tat ✽.User Closes PromptDisplay \"Prompt\"(file:///C:/Users/User/eclipse-workspace/JavaBasic/CucumberSalesForceFramework/features/Oppurtunities.feature:57)\r\n","duration":16954300,"status":"failed"},"line":57,"name":"User Closes PromptDisplay \"Prompt\"","match":{"arguments":[{"val":"\"Prompt\"","offset":26}],"location":"com.training.steps.Steps.user_closes_prompt_display(java.lang.String)"},"keyword":"Then "},{"result":{"status":"skipped"},"line":58,"name":"User Clicks on \"StuckOppurtunity\"","match":{"arguments":[{"val":"\"StuckOppurtunity\"","offset":15}],"location":"com.training.steps.Steps.user_clicks_on(java.lang.String)"},"keyword":"Then "},{"result":{"status":"skipped"},"line":59,"name":"Check for text displayed \"StuckOppurtunityText\" \"Stuck Opportunities\"","match":{"arguments":[{"val":"\"StuckOppurtunityText\"","offset":25},{"val":"\"Stuck Opportunities\"","offset":48}],"location":"com.training.steps.Steps.check_for_text_displayed(java.lang.String,java.lang.String)"},"keyword":"And "}],"tags":[{"name":"@TC18"}]},{"start_timestamp":"2023-09-01T18:39:43.634Z","before":[{"result":{"duration":201579800,"status":"passed"},"match":{"location":"com.training.steps.Steps.setup()"}}],"line":62,"name":"Testing Quarterly Summary","description":"","id":"oppurtunities-scenarios-of-salesforce-application;testing-quarterly-summary","type":"scenario","keyword":"Scenario","steps":[{"result":{"duration":1982000,"status":"passed"},"line":63,"name":"User is in the \"LoginPage\"","match":{"arguments":[{"val":"\"LoginPage\"","offset":15}],"location":"com.training.steps.Steps.user_is_in_the(java.lang.String)"},"keyword":"Given "},{"result":{"duration":699786600,"status":"passed"},"line":64,"name":"User enter into Textbox \"Username\" \"Myself@HomeComp.org\"","match":{"arguments":[{"val":"\"Username\"","offset":24},{"val":"\"Myself@HomeComp.org\"","offset":35}],"location":"com.training.steps.Steps.user_enter_into_textbox(java.lang.String,java.lang.String)"},"keyword":"When "},{"result":{"duration":600481700,"status":"passed"},"line":65,"name":"User enter into Textbox \"Password\" \"Really82\"","match":{"arguments":[{"val":"\"Password\"","offset":24},{"val":"\"Really82\"","offset":35}],"location":"com.training.steps.Steps.user_enter_into_textbox(java.lang.String,java.lang.String)"},"keyword":"When "},{"result":{"duration":2100631200,"status":"passed"},"line":66,"name":"User Clicks on Button \"Login\"","match":{"arguments":[{"val":"\"Login\"","offset":22}],"location":"com.training.steps.Steps.user_clicks_on_button(java.lang.String)"},"keyword":"Then "},{"result":{"duration":1998900,"status":"passed"},"line":67,"name":"User is in the \"OppurtunitiesPage\"","match":{"arguments":[{"val":"\"OppurtunitiesPage\"","offset":15}],"location":"com.training.steps.Steps.user_is_in_the(java.lang.String)"},"keyword":"Given "},{"result":{"duration":2614129800,"status":"passed"},"line":68,"name":"User Clicks on Tab \"Oppurtunities\"","match":{"arguments":[{"val":"\"Oppurtunities\"","offset":19}],"location":"com.training.steps.Steps.user_clicks_on_tab(java.lang.String)"},"keyword":"Then "},{"result":{"error_message":"org.openqa.selenium.NoSuchElementException: no such element: Unable to locate element: {\"method\":\"xpath\",\"selector\":\"//a[@id='tryLexDialogX']\"}\n  (Session info: chrome=116.0.5845.112)\nFor documentation on this error, please visit: https://www.seleniumhq.org/exceptions/no_such_element.html\nBuild info: version: '3.141.59', revision: 'e82be7d358', time: '2018-11-14T08:17:03'\nSystem info: host: 'DESKTOP-SHP5I9E', ip: '192.168.1.68', os.name: 'Windows 10', os.arch: 'amd64', os.version: '10.0', java.version: '17.0.6'\nDriver info: org.openqa.selenium.chrome.ChromeDriver\nCapabilities {acceptInsecureCerts: false, browserName: chrome, browserVersion: 116.0.5845.112, chrome: {chromedriverVersion: 116.0.5845.96 (1a3918166880..., userDataDir: C:\\Users\\User\\AppData\\Local...}, fedcm:accounts: true, goog:chromeOptions: {debuggerAddress: localhost:60533}, javascriptEnabled: true, networkConnectionEnabled: false, pageLoadStrategy: normal, platform: WINDOWS, platformName: WINDOWS, proxy: Proxy(), setWindowRect: true, strictFileInteractability: false, timeouts: {implicit: 0, pageLoad: 300000, script: 30000}, unhandledPromptBehavior: dismiss and notify, webauthn:extension:credBlob: true, webauthn:extension:largeBlob: true, webauthn:extension:minPinLength: true, webauthn:extension:prf: true, webauthn:virtualAuthenticators: true}\nSession ID: 671b82b876cb7e1fa2a24321bb861806\n*** Element info: {Using=xpath, value=//a[@id='tryLexDialogX']}\r\n\tat java.base/jdk.internal.reflect.NativeConstructorAccessorImpl.newInstance0(Native Method)\r\n\tat java.base/jdk.internal.reflect.NativeConstructorAccessorImpl.newInstance(NativeConstructorAccessorImpl.java:77)\r\n\tat java.base/jdk.internal.reflect.DelegatingConstructorAccessorImpl.newInstance(DelegatingConstructorAccessorImpl.java:45)\r\n\tat java.base/java.lang.reflect.Constructor.newInstanceWithCaller(Constructor.java:499)\r\n\tat java.base/java.lang.reflect.Constructor.newInstance(Constructor.java:480)\r\n\tat org.openqa.selenium.remote.http.W3CHttpResponseCodec.createException(W3CHttpResponseCodec.java:187)\r\n\tat org.openqa.selenium.remote.http.W3CHttpResponseCodec.decode(W3CHttpResponseCodec.java:122)\r\n\tat org.openqa.selenium.remote.http.W3CHttpResponseCodec.decode(W3CHttpResponseCodec.java:49)\r\n\tat org.openqa.selenium.remote.HttpCommandExecutor.execute(HttpCommandExecutor.java:158)\r\n\tat org.openqa.selenium.remote.service.DriverCommandExecutor.execute(DriverCommandExecutor.java:83)\r\n\tat org.openqa.selenium.remote.RemoteWebDriver.execute(RemoteWebDriver.java:552)\r\n\tat org.openqa.selenium.remote.RemoteWebDriver.findElement(RemoteWebDriver.java:323)\r\n\tat org.openqa.selenium.remote.RemoteWebDriver.findElementByXPath(RemoteWebDriver.java:428)\r\n\tat org.openqa.selenium.By$ByXPath.findElement(By.java:353)\r\n\tat org.openqa.selenium.remote.RemoteWebDriver.findElement(RemoteWebDriver.java:315)\r\n\tat com.training.base.BasePage.getElement(BasePage.java:45)\r\n\tat com.training.base.BasePage.promptclose(BasePage.java:204)\r\n\tat com.training.steps.Steps.user_closes_prompt_display(Steps.java:105)\r\n\tat ✽.User Closes PromptDisplay \"Prompt\"(file:///C:/Users/User/eclipse-workspace/JavaBasic/CucumberSalesForceFramework/features/Oppurtunities.feature:69)\r\n","duration":14956700,"status":"failed"},"line":69,"name":"User Closes PromptDisplay \"Prompt\"","match":{"arguments":[{"val":"\"Prompt\"","offset":26}],"location":"com.training.steps.Steps.user_closes_prompt_display(java.lang.String)"},"keyword":"Then "},{"result":{"status":"skipped"},"line":70,"name":"User selects value from Dropdown \"Interval\" \"Current and Next FQ\"","match":{"arguments":[{"val":"\"Interval\"","offset":33},{"val":"\"Current and Next FQ\"","offset":44}],"location":"com.training.steps.Steps.user_selects_value_from_dropdown(java.lang.String,java.lang.String)"},"keyword":"Then "},{"result":{"status":"skipped"},"line":71,"name":"User selects value from Dropdown \"Include\" \"All Opportunities\"","match":{"arguments":[{"val":"\"Include\"","offset":33},{"val":"\"All Opportunities\"","offset":43}],"location":"com.training.steps.Steps.user_selects_value_from_dropdown(java.lang.String,java.lang.String)"},"keyword":"Then "},{"result":{"status":"skipped"},"line":72,"name":"User Clicks on Button \"RunReport\"","match":{"arguments":[{"val":"\"RunReport\"","offset":22}],"location":"com.training.steps.Steps.user_clicks_on_button(java.lang.String)"},"keyword":"Then "}],"tags":[{"name":"@TC19"}]}],"name":"Oppurtunities scenarios of SalesForce application","description":"","id":"oppurtunities-scenarios-of-salesforce-application","keyword":"Feature","uri":"file:features/Oppurtunities.feature","tags":[]}]